ambient_aprs/__init__.py
ambient_aprs/ambient_aprs.py
ambient_aprs-0.13.0.dist-info/LICENSE
ambient_aprs-0.13.0.dist-info/METADATA
ambient_aprs-0.13.0.dist-info/WHEEL
ambient_aprs-0.13.0.dist-info/top_level.txt
ambient_aprs-0.13.0.dist-info/RECORD
