Metadata-Version: 2.1
Name: ambient-aprs
Version: 0.13.0
Summary: A Python class for sending Ambient Weather API Data as APRS packets.
Home-page: https://github.com/avryhof/ambient_aprs
Author: Amos Vryhof
Author-email: amos@vryhofresearch.com
License: MIT
Platform: UNKNOWN
Classifier: Development Status :: 5 - Production/Stable
Classifier: Intended Audience :: Developers
Classifier: License :: OSI Approved :: MIT License
Classifier: Programming Language :: Python :: 3
License-File: LICENSE
Requires-Dist: ambient-api
